{"bankroll": 37.27, "bankroll_ref": 37.27, "trades": [], "wins": 0, "losses": 0, "pnl": 0.0, "best_streak": 0, "worst_streak": 0, "consec": 0, "daily_start": 37.27, "daily_ts": 1781631138.3968706, "daily_pause_until": 0, "paper_mode": false, "skipped": 5175, "pass_reasons": [{"ts": 1781630982, "reason": "ETH: prix spot p\u00e9rim\u00e9 5s", "dir": null, "slot_end": 1781631000, "open_px": 65808.0, "resolved": null}, {"ts": 1781630982, "reason": "XRP: delta -0.232%<0", "dir": "UP", "slot_end": 1781631000, "open_px": 65808.0, "resolved": "LOSS"}, {"ts": 1781630984, "reason": "BTC: delta -0.054%<0 (\u2192 skip: delta n\u00e9gatif LOSS garanti)", "dir": "UP", "slot_end": 1781631000, "open_px": 65808.0, "resolved": "LOSS"}, {"ts": 1781630984, "reason": "ETH: delta -0.127%<0", "dir": "UP", "slot_end": 1781631000, "open_px": 65808.0, "resolved": "LOSS"}, {"ts": 1781630984, "reason": "XRP: delta -0.207%<0", "dir": "UP", "slot_end": 1781631000, "open_px": 65808.0, "resolved": "LOSS"}, {"ts": 1781630986, "reason": "BTC: delta -0.051%<0 (\u2192 skip: delta n\u00e9gatif LOSS garanti)", "dir": "UP", "slot_end": 1781631000, "open_px": 65808.0, "resolved": "LOSS"}, {"ts": 1781630986, "reason": "ETH: delta -0.127%<0", "dir": "UP", "slot_end": 1781631000, "open_px": 65808.0, "resolved": "LOSS"}, {"ts": 1781630986, "reason": "SOL: delta -0.058%<0", "dir": "UP", "slot_end": 1781631000, "open_px": 65808.0, "resolved": "LOSS"}, {"ts": 1781630986, "reason": "XRP: delta -0.208%<0", "dir": "UP", "slot_end": 1781631000, "open_px": 65808.0, "resolved": "LOSS"}, {"ts": 1781630988, "reason": "BTC: delta -0.060%<0 (\u2192 skip: delta n\u00e9gatif LOSS garanti)", "dir": "UP", "slot_end": 1781631000, "open_px": 65808.0, "resolved": "LOSS"}, {"ts": 1781630988, "reason": "ETH: delta -0.134%<0", "dir": "UP", "slot_end": 1781631000, "open_px": 65808.0, "resolved": "LOSS"}, {"ts": 1781630988, "reason": "SOL: delta -0.063%<0", "dir": "UP", "slot_end": 1781631000, "open_px": 65808.0, "resolved": "LOSS"}, {"ts": 1781630988, "reason": "XRP: delta -0.220%<0", "dir": "UP", "slot_end": 1781631000, "open_px": 65808.0, "resolved": "LOSS"}, {"ts": 1781630990, "reason": "BTC: delta -0.059%<0 (\u2192 skip: delta n\u00e9gatif LOSS garanti)", "dir": "UP", "slot_end": 1781631000, "open_px": 65808.0, "resolved": "LOSS"}, {"ts": 1781630990, "reason": "ETH: delta -0.134%<0", "dir": "UP", "slot_end": 1781631000, "open_px": 65808.0, "resolved": "LOSS"}, {"ts": 1781630990, "reason": "SOL: delta -0.063%<0", "dir": "UP", "slot_end": 1781631000, "open_px": 65808.0, "resolved": "LOSS"}, {"ts": 1781630990, "reason": "XRP: delta -0.219%<0", "dir": "UP", "slot_end": 1781631000, "open_px": 65808.0, "resolved": "LOSS"}, {"ts": 1781630992, "reason": "BTC: delta -0.057%<0 (\u2192 skip: delta n\u00e9gatif LOSS garanti)", "dir": "UP", "slot_end": 1781631000, "open_px": 65808.0, "resolved": "LOSS"}, {"ts": 1781630992, "reason": "ETH: delta -0.132%<0", "dir": "UP", "slot_end": 1781631000, "open_px": 65808.0, "resolved": "LOSS"}, {"ts": 1781630992, "reason": "SOL: delta -0.060%<0", "dir": "UP", "slot_end": 1781631000, "open_px": 65808.0, "resolved": "LOSS"}, {"ts": 1781630992, "reason": "XRP: delta -0.219%<0", "dir": "UP", "slot_end": 1781631000, "open_px": 65808.0, "resolved": "LOSS"}, {"ts": 1781630994, "reason": "BTC: delta -0.057%<0 (\u2192 skip: delta n\u00e9gatif LOSS garanti)", "dir": "UP", "slot_end": 1781631000, "open_px": 65808.0, "resolved": "LOSS"}, {"ts": 1781630994, "reason": "ETH: delta -0.132%<0", "dir": "UP", "slot_end": 1781631000, "open_px": 65808.0, "resolved": "LOSS"}, {"ts": 1781630994, "reason": "SOL: delta -0.060%<0", "dir": "UP", "slot_end": 1781631000, "open_px": 65808.0, "resolved": "LOSS"}, {"ts": 1781630994, "reason": "XRP: delta -0.205%<0", "dir": "UP", "slot_end": 1781631000, "open_px": 65808.0, "resolved": "LOSS"}, {"ts": 1781631280, "reason": "BTC: ret3s -0.089%<-0.055% (chute brutale)", "dir": "UP", "slot_end": 1781631300, "open_px": 65741.99, "resolved": null}, {"ts": 1781631280, "reason": "XRP: votes 1/5 < 2 (\u2192 skip: consensus faible)", "dir": "UP", "slot_end": 1781631300, "open_px": 65741.99, "resolved": null}, {"ts": 1781631280, "reason": "ETH: token 0.99$>0.8$ (d\u00e9j\u00e0 pric\u00e9)", "dir": "UP", "slot_end": 1781631300, "open_px": 65741.99, "resolved": null}, {"ts": 1781631282, "reason": "BTC: ret3s -0.091%<-0.055% (chute brutale)", "dir": "UP", "slot_end": 1781631300, "open_px": 65741.99, "resolved": null}, {"ts": 1781631282, "reason": "ETH: token 0.99$>0.8$ (d\u00e9j\u00e0 pric\u00e9)", "dir": "UP", "slot_end": 1781631300, "open_px": 65741.99, "resolved": null}, {"ts": 1781631284, "reason": "BTC: ret3s -0.091%<-0.055% (chute brutale)", "dir": "UP", "slot_end": 1781631300, "open_px": 65741.99, "resolved": null}, {"ts": 1781631284, "reason": "ETH: token 0.99$>0.8$ (d\u00e9j\u00e0 pric\u00e9)", "dir": "UP", "slot_end": 1781631300, "open_px": 65741.99, "resolved": null}, {"ts": 1781631286, "reason": "BTC: ret3s -0.091%<-0.055% (chute brutale)", "dir": "UP", "slot_end": 1781631300, "open_px": 65741.99, "resolved": null}, {"ts": 1781631286, "reason": "XRP: votes 1/5 < 2 (\u2192 skip: consensus faible)", "dir": "UP", "slot_end": 1781631300, "open_px": 65741.99, "resolved": null}, {"ts": 1781631286, "reason": "SOL: token 0.99$>0.8$ (d\u00e9j\u00e0 pric\u00e9)", "dir": "UP", "slot_end": 1781631300, "open_px": 65741.99, "resolved": null}, {"ts": 1781631286, "reason": "ETH: token 0.99$>0.8$ (d\u00e9j\u00e0 pric\u00e9)", "dir": "UP", "slot_end": 1781631300, "open_px": 65741.99, "resolved": null}, {"ts": 1781631288, "reason": "BTC: ret3s -0.082%<-0.055% (chute brutale)", "dir": "UP", "slot_end": 1781631300, "open_px": 65741.99, "resolved": null}, {"ts": 1781631288, "reason": "SOL: token 0.99$>0.8$ (d\u00e9j\u00e0 pric\u00e9)", "dir": "UP", "slot_end": 1781631300, "open_px": 65741.99, "resolved": null}, {"ts": 1781631288, "reason": "XRP: votes 1/5 < 2 (\u2192 skip: consensus faible)", "dir": "UP", "slot_end": 1781631300, "open_px": 65741.99, "resolved": null}, {"ts": 1781631288, "reason": "ETH: token 0.99$>0.8$ (d\u00e9j\u00e0 pric\u00e9)", "dir": "UP", "slot_end": 1781631300, "open_px": 65741.99, "resolved": null}, {"ts": 1781631290, "reason": "BTC: ret3s -0.082%<-0.055% (chute brutale)", "dir": "UP", "slot_end": 1781631300, "open_px": 65741.99, "resolved": null}, {"ts": 1781631290, "reason": "SOL: token 0.99$>0.8$ (d\u00e9j\u00e0 pric\u00e9)", "dir": "UP", "slot_end": 1781631300, "open_px": 65741.99, "resolved": null}, {"ts": 1781631290, "reason": "ETH: token 0.99$>0.8$ (d\u00e9j\u00e0 pric\u00e9)", "dir": "UP", "slot_end": 1781631300, "open_px": 65741.99, "resolved": null}, {"ts": 1781631290, "reason": "XRP: token 0.89$>0.8$ (d\u00e9j\u00e0 pric\u00e9)", "dir": "UP", "slot_end": 1781631300, "open_px": 65741.99, "resolved": null}, {"ts": 1781631292, "reason": "SOL: token 0.99$>0.8$ (d\u00e9j\u00e0 pric\u00e9)", "dir": "UP", "slot_end": 1781631300, "open_px": 65741.99, "resolved": null}, {"ts": 1781631292, "reason": "XRP: EV +12.8% insuffisant", "dir": "UP", "slot_end": 1781631300, "open_px": 65741.99, "resolved": null}, {"ts": 1781631292, "reason": "ETH: token 0.99$>0.8$ (d\u00e9j\u00e0 pric\u00e9)", "dir": "UP", "slot_end": 1781631300, "open_px": 65741.99, "resolved": null}, {"ts": 1781631294, "reason": "XRP: token 0.46$<0.51$ (incertain)", "dir": "UP", "slot_end": 1781631300, "open_px": 65741.99, "resolved": null}, {"ts": 1781631294, "reason": "ETH: token 0.99$>0.8$ (d\u00e9j\u00e0 pric\u00e9)", "dir": "UP", "slot_end": 1781631300, "open_px": 65741.99, "resolved": null}, {"ts": 1781631294, "reason": "SOL: token 0.99$>0.8$ (d\u00e9j\u00e0 pric\u00e9)", "dir": "UP", "slot_end": 1781631300, "open_px": 65741.99, "resolved": null}], "calib_factor": 1.0, "killed": false, "version": "12.8", "saved_at": 1781631318, "oracle_patterns": [{"gap": -0.004830152320107174, "delta": -0.026272176642691346, "ret3s": -0.09187272380800646, "votes": 0, "filter": "ret3s_brutal", "asset": "BTC", "direction": "DOWN", "result": "WIN", "ts": 1781630676, "slot_end": 1781630700, "open_px": 65765.59, "v": "12.8"}, {"gap": 0.038706179766923, "delta": -0.02624474316215037, "ret3s": -0.048346861278868926, "votes": 0, "filter": "delta_neg", "asset": "BTC", "direction": "UP", "result": "LOSS", "ts": 1781630678, "slot_end": 1781630700, "open_px": 65765.59, "v": "12.8"}, {"gap": 0.08098035340146836, "delta": 0.05118336424252435, "ret3s": -0.007288711467939861, "votes": 5, "filter": "tokenmax", "token": 0.92, "direction": "UP", "result": "LOSS", "ts": 1781630680, "slot_end": 1781630700, "open_px": 65765.59, "asset": "ETH", "v": "12.8"}, {"gap": 0.06848512158584354, "delta": 0.026023927434390578, "ret3s": -0.008209506608651915, "votes": 5, "filter": "tokenmin", "token": 0.06, "direction": "UP", "result": "LOSS", "ts": 1781630680, "slot_end": 1781630700, "open_px": 65765.59, "asset": "BTC", "v": "12.8"}, {"gap": 0.06683057478241268, "delta": 0.0276777995236575, "ret3s": -0.008209506608651915, "votes": 5, "filter": "tokenmin", "token": 0.07, "direction": "UP", "result": "LOSS", "ts": 1781630682, "slot_end": 1781630700, "open_px": 65765.59, "asset": "BTC", "v": "12.8"}, {"gap": 0.08307148245380444, "delta": 0.04909290145841353, "ret3s": -0.006728079077349971, "votes": 5, "filter": "tokenmax", "token": 0.94, "direction": "UP", "result": "LOSS", "ts": 1781630682, "slot_end": 1781630700, "open_px": 65765.59, "asset": "ETH", "v": "12.8"}, {"gap": 0.09482955417993441, "delta": 0.04799768907651293, "ret3s": 0.01065350864896995, "votes": 3, "filter": "tokenmax", "token": 0.97, "direction": "UP", "result": "LOSS", "ts": 1781630684, "slot_end": 1781630700, "open_px": 65765.59, "asset": "ETH", "v": "12.8"}, {"gap": 0.08860902979648413, "delta": 0.02233393476091647, "ret3s": 0.016420361247945648, "votes": 3, "filter": "tokenmin", "token": 0.22, "direction": "UP", "result": "LOSS", "ts": 1781630684, "slot_end": 1781630700, "open_px": 65765.59, "asset": "BTC", "v": "12.8"}, {"gap": 0.06800852832055351, "delta": 0.02650032073989003, "ret3s": -0.016417665407977178, "votes": 5, "filter": "tokenmin", "token": 0.06, "direction": "UP", "result": "LOSS", "ts": 1781630686, "slot_end": 1781630700, "open_px": 65765.59, "asset": "BTC", "v": "12.8"}, {"gap": 0.062632119578413, "delta": 0.08063588510411462, "ret3s": -0.013644426251883088, "votes": 5, "filter": "tokenmin", "token": 0.41, "direction": "UP", "result": "LOSS", "ts": 1781630686, "slot_end": 1781630700, "open_px": 65765.59, "asset": "SOL", "v": "12.8"}, {"gap": 0.07742554895269452, "delta": 0.05361520075621974, "ret3s": -0.011773676302394898, "votes": 5, "filter": "tokenmax", "token": 0.95, "direction": "UP", "result": "LOSS", "ts": 1781630686, "slot_end": 1781630700, "open_px": 65765.59, "asset": "ETH", "v": "12.8"}, {"gap": 0.07589990948164915, "delta": 0.06736746731814544, "ret3s": -0.013644426251883088, "votes": 4, "filter": "tokenmin", "token": 0.38, "direction": "UP", "result": "LOSS", "ts": 1781630688, "slot_end": 1781630700, "open_px": 65765.59, "asset": "SOL", "v": "12.8"}, {"gap": 0.0789931445169919, "delta": 0.05204800270143781, "ret3s": -0.005606858309078572, "votes": 4, "filter": "tokenmax", "token": 0.96, "direction": "UP", "result": "LOSS", "ts": 1781630688, "slot_end": 1781630700, "open_px": 65765.59, "asset": "ETH", "v": "12.8"}, {"gap": 0.07464683106714998, "delta": 0.019865211720394932, "ret3s": -0.008209506608651915, "votes": 4, "filter": "tokenmin", "token": 0.03, "direction": "UP", "result": "LOSS", "ts": 1781630688, "slot_end": 1781630700, "open_px": 65765.59, "asset": "BTC", "v": "12.8"}, {"gap": 0.08176112848089236, "delta": 0.049280840520195324, "ret3s": 0.0, "votes": 4, "filter": "tokenmax", "token": 0.97, "direction": "UP", "result": "LOSS", "ts": 1781630690, "slot_end": 1781630700, "open_px": 65765.59, "asset": "ETH", "v": "12.8"}, {"gap": 0.07658486140931024, "delta": 0.06668257847688823, "ret3s": 0.0, "votes": 4, "filter": "tokenmin", "token": 0.39, "direction": "UP", "result": "LOSS", "ts": 1781630690, "slot_end": 1781630700, "open_px": 65765.59, "asset": "SOL", "v": "12.8"}, {"gap": 0.07279074516213534, "delta": 0.02172031599657815, "ret3s": 0.0, "votes": 4, "filter": "tokenmin", "token": 0.04, "direction": "UP", "result": "LOSS", "ts": 1781630690, "slot_end": 1781630700, "open_px": 65765.59, "asset": "BTC", "v": "12.8"}, {"gap": 0.07967402957443531, "delta": 0.050806300300850565, "ret3s": -0.0005607172695306743, "votes": 3, "filter": "tokenmax", "token": 0.98, "direction": "UP", "result": "LOSS", "ts": 1781630692, "slot_end": 1781630700, "open_px": 65765.59, "asset": "ETH", "v": "12.8"}, {"gap": 0.10527328048381618, "delta": 0.022102089263796657, "ret3s": 0.032840722495891296, "votes": 1, "filter": "tokenmin", "token": 0.19, "direction": "UP", "result": "LOSS", "ts": 1781630692, "slot_end": 1781630700, "open_px": 65765.59, "asset": "BTC", "v": "12.8"}, {"gap": 0.09280387055250569, "delta": 0.03456269127426097, "ret3s": 0.008208158909955594, "votes": 1, "filter": "tokenmin", "token": 0.29, "direction": "UP", "result": "LOSS", "ts": 1781630694, "slot_end": 1781630700, "open_px": 65765.59, "asset": "BTC", "v": "12.8"}, {"gap": 0.07665614732404478, "delta": 0.053823403030846324, "ret3s": 0.0, "votes": 3, "filter": "tokenmax", "token": 0.98, "direction": "UP", "result": "LOSS", "ts": 1781630694, "slot_end": 1781630700, "open_px": 65765.59, "asset": "ETH", "v": "12.8"}, {"gap": 0.09332200094044134, "delta": 0.07725610249807177, "ret3s": 0.013644426251863698, "votes": 2, "filter": "tokenmax", "token": 0.84, "direction": "UP", "result": "LOSS", "ts": 1781630694, "slot_end": 1781630700, "open_px": 65765.59, "asset": "SOL", "v": "12.8"}, {"gap": -4.4452283594983e-05, "delta": -0.05436307293225455, "ret3s": -0.07638252832556959, "votes": 0, "filter": "ret3s_brutal", "asset": "BTC", "direction": "DOWN", "result": "WIN", "ts": 1781630976, "slot_end": 1781631000, "open_px": 65808.0, "v": "12.8"}, {"gap": 0.038273394218438415, "delta": -0.054475595418813666, "ret3s": -0.04121673003803167, "votes": 0, "filter": "delta_neg", "asset": "BTC", "direction": "UP", "result": "LOSS", "ts": 1781630978, "slot_end": 1781631000, "open_px": 65808.0, "v": "12.8"}, {"gap": 0.036708100454469525, "delta": -0.05291172842381025, "ret3s": -0.04121673003803167, "votes": 0, "filter": "delta_neg", "asset": "BTC", "direction": "UP", "result": "LOSS", "ts": 1781630980, "slot_end": 1781631000, "open_px": 65808.0, "v": "12.8"}, {"gap": 0.08144532972439063, "delta": -0.1303220742290299, "ret3s": 0.0, "votes": 0, "filter": "delta_neg", "direction": "UP", "result": "LOSS", "ts": 1781630980, "slot_end": 1781631000, "open_px": 65808.0, "asset": "ETH", "v": "12.8"}, {"gap": 0.12212825695761219, "delta": -0.24434057758751015, "ret3s": 0.04935834155971816, "votes": 0, "filter": "delta_neg", "direction": "UP", "result": "LOSS", "ts": 1781630980, "slot_end": 1781631000, "open_px": 65808.0, "asset": "BTC", "v": "12.8"}, {"gap": 0.036121371938028606, "delta": -0.0523331258189338, "ret3s": -0.04122433460075425, "votes": 0, "filter": "delta_neg", "asset": "BTC", "direction": "UP", "result": "LOSS", "ts": 1781630982, "slot_end": 1781631000, "open_px": 65808.0, "v": "12.8"}, {"gap": 0.10954677711587249, "delta": -0.23180357329043916, "ret3s": 0.04935834155971816, "votes": 0, "filter": "delta_neg", "direction": "UP", "result": "LOSS", "ts": 1781630982, "slot_end": 1781631000, "open_px": 65808.0, "asset": "BTC", "v": "12.8"}, {"gap": 0.035224472529751215, "delta": -0.053596486601486575, "ret3s": -0.043368827888794224, "votes": 0, "filter": "delta_neg", "asset": "BTC", "direction": "UP", "result": "LOSS", "ts": 1781630984, "slot_end": 1781631000, "open_px": 65808.0, "v": "12.8"}, {"gap": 0.07715825557485394, "delta": -0.1271649462812007, "ret3s": -0.0011224730325843713, "votes": 0, "filter": "delta_neg", "direction": "UP", "result": "LOSS", "ts": 1781630984, "slot_end": 1781631000, "open_px": 65808.0, "asset": "ETH", "v": "12.8"}, {"gap": 0.06824266851792726, "delta": -0.20703662794570493, "ret3s": -0.01644466370662539, "votes": 0, "filter": "delta_neg", "direction": "UP", "result": "LOSS", "ts": 1781630984, "slot_end": 1781631000, "open_px": 65808.0, "asset": "BTC", "v": "12.8"}, {"gap": 0.028016000093415087, "delta": -0.05129869080057959, "ret3s": -0.04827377160058159, "votes": 0, "filter": "delta_neg", "asset": "BTC", "direction": "UP", "result": "LOSS", "ts": 1781630986, "slot_end": 1781631000, "open_px": 65808.0, "v": "12.8"}, {"gap": 0.07651961199859952, "delta": -0.12652760252867348, "ret3s": -0.0011224730325843713, "votes": 0, "filter": "delta_neg", "direction": "UP", "result": "LOSS", "ts": 1781630986, "slot_end": 1781631000, "open_px": 65808.0, "asset": "ETH", "v": "12.8"}, {"gap": 0.07854168123871864, "delta": -0.058005218882473446, "ret3s": 0.0, "votes": 0, "filter": "delta_neg", "direction": "UP", "result": "LOSS", "ts": 1781630986, "slot_end": 1781631000, "open_px": 65808.0, "asset": "SOL", "v": "12.8"}, {"gap": 0.06929804773105495, "delta": -0.20808909279970084, "ret3s": -0.01644466370662539, "votes": 0, "filter": "delta_neg", "direction": "UP", "result": "LOSS", "ts": 1781630986, "slot_end": 1781631000, "open_px": 65808.0, "asset": "BTC", "v": "12.8"}, {"gap": 0.03725469348250987, "delta": -0.05960156302119474, "ret3s": -0.043043684320361375, "votes": 0, "filter": "delta_neg", "asset": "BTC", "direction": "UP", "result": "LOSS", "ts": 1781630988, "slot_end": 1781631000, "open_px": 65808.0, "v": "12.8"}, {"gap": 0.08432425620182446, "delta": -0.1343158043594369, "ret3s": 0.0, "votes": 0, "filter": "delta_neg", "direction": "UP", "result": "LOSS", "ts": 1781630988, "slot_end": 1781631000, "open_px": 65808.0, "asset": "ETH", "v": "12.8"}, {"gap": 0.08368635835008478, "delta": -0.06314261251497519, "ret3s": 0.0, "votes": 0, "filter": "delta_neg", "direction": "UP", "result": "LOSS", "ts": 1781630988, "slot_end": 1781631000, "open_px": 65808.0, "asset": "SOL", "v": "12.8"}, {"gap": 0.07260114150745683, "delta": -0.21958922258730426, "ret3s": -0.00822368421052541, "votes": 0, "filter": "delta_neg", "direction": "UP", "result": "LOSS", "ts": 1781630988, "slot_end": 1781631000, "open_px": 65808.0, "asset": "BTC", "v": "12.8"}, {"gap": 0.03638040225897906, "delta": -0.058728110654383096, "ret3s": -0.04305888755363565, "votes": 0, "filter": "delta_neg", "asset": "BTC", "direction": "UP", "result": "LOSS", "ts": 1781630990, "slot_end": 1781631000, "open_px": 65808.0, "v": "12.8"}, {"gap": 0.08432819153018185, "delta": -0.1343197310906849, "ret3s": 0.0, "votes": 0, "filter": "delta_neg", "direction": "UP", "result": "LOSS", "ts": 1781630990, "slot_end": 1781631000, "open_px": 65808.0, "asset": "ETH", "v": "12.8"}, {"gap": 0.08320742609961755, "delta": -0.0626643805993109, "ret3s": 0.0, "votes": 0, "filter": "delta_neg", "direction": "UP", "result": "LOSS", "ts": 1781630990, "slot_end": 1781631000, "open_px": 65808.0, "asset": "SOL", "v": "12.8"}, {"gap": 0.07160407718777075, "delta": -0.21859505957465739, "ret3s": -0.00822368421052541, "votes": 0, "filter": "delta_neg", "direction": "UP", "result": "LOSS", "ts": 1781630990, "slot_end": 1781631000, "open_px": 65808.0, "asset": "BTC", "v": "12.8"}, {"gap": 0.03474941908697962, "delta": -0.057106255377439144, "ret3s": -0.043051289211569005, "votes": 0, "filter": "delta_neg", "asset": "BTC", "direction": "UP", "result": "LOSS", "ts": 1781630992, "slot_end": 1781631000, "open_px": 65808.0, "v": "12.8"}, {"gap": 0.08239991771242176, "delta": -0.13239563278055577, "ret3s": 0.0, "votes": 0, "filter": "delta_neg", "direction": "UP", "result": "LOSS", "ts": 1781630992, "slot_end": 1781631000, "open_px": 65808.0, "asset": "ETH", "v": "12.8"}, {"gap": 0.08072777955679755, "delta": -0.06018828680717614, "ret3s": 0.0, "votes": 0, "filter": "delta_neg", "direction": "UP", "result": "LOSS", "ts": 1781630992, "slot_end": 1781631000, "open_px": 65808.0, "asset": "SOL", "v": "12.8"}, {"gap": 0.08803596783402212, "delta": -0.21856653879915056, "ret3s": 0.016448721111931738, "votes": 0, "filter": "delta_neg", "direction": "UP", "result": "LOSS", "ts": 1781630992, "slot_end": 1781631000, "open_px": 65808.0, "asset": "BTC", "v": "12.8"}, {"gap": 0.03491867758951313, "delta": -0.05726775436530276, "ret3s": -0.043043684320361375, "votes": 0, "filter": "delta_neg", "asset": "BTC", "direction": "UP", "result": "LOSS", "ts": 1781630994, "slot_end": 1781631000, "open_px": 65808.0, "v": "12.8"}, {"gap": 0.0694829446613608, "delta": -0.13239787662698868, "ret3s": -0.012908584770115961, "votes": 0, "filter": "delta_neg", "direction": "UP", "result": "LOSS", "ts": 1781630994, "slot_end": 1781631000, "open_px": 65808.0, "asset": "ETH", "v": "12.8"}, {"gap": 0.0808866268766673, "delta": -0.060346910214441836, "ret3s": 0.0, "votes": 0, "filter": "delta_neg", "direction": "UP", "result": "LOSS", "ts": 1781630994, "slot_end": 1781631000, "open_px": 65808.0, "asset": "SOL", "v": "12.8"}, {"gap": 0.07483509609957541, "delta": -0.20540436967505793, "ret3s": 0.0, "votes": 0, "filter": "delta_neg", "direction": "UP", "result": "LOSS", "ts": 1781630994, "slot_end": 1781631000, "open_px": 65808.0, "asset": "BTC", "v": "12.8"}, {"gap": -0.008060906241658264, "delta": 0.12051646149837861, "ret3s": -0.08856644967963703, "votes": 0, "filter": "ret3s_brutal", "asset": "BTC", "direction": "UP", "result": null, "ts": 1781631280, "slot_end": 1781631300, "open_px": 65741.99, "v": "12.8"}, {"gap": 0.07633503030963269, "delta": 0.18779987335742146, "ret3s": 0.024673081667897605, "votes": 1, "filter": "votes_min", "direction": "UP", "result": null, "ts": 1781631280, "slot_end": 1781631300, "open_px": 65741.99, "asset": "BTC", "v": "12.8"}, {"gap": 0.07368941395905168, "delta": 0.2003474546666906, "ret3s": 0.003921151250003436, "votes": 1, "filter": "tokenmax", "token": 0.99, "direction": "UP", "result": null, "ts": 1781631280, "slot_end": 1781631300, "open_px": 65741.99, "asset": "ETH", "v": "12.8"}, {"gap": -0.007260342626650483, "delta": 0.11727874982869814, "ret3s": -0.09099750679898214, "votes": 0, "filter": "ret3s_brutal", "asset": "BTC", "direction": "UP", "result": null, "ts": 1781631282, "slot_end": 1781631300, "open_px": 65741.99, "v": "12.8"}, {"gap": 0.08559785708342199, "delta": 0.1923537439939605, "ret3s": 0.004481165102922686, "votes": 2, "filter": "tokenmax", "token": 0.99, "direction": "UP", "result": null, "ts": 1781631282, "slot_end": 1781631300, "open_px": 65741.99, "asset": "ETH", "v": "12.8"}, {"gap": -0.007475264014336318, "delta": 0.11718942307422403, "ret3s": -0.09128620870203372, "votes": 0, "filter": "ret3s_brutal", "asset": "BTC", "direction": "UP", "result": null, "ts": 1781631284, "slot_end": 1781631300, "open_px": 65741.99, "v": "12.8"}, {"gap": 0.08236871968443457, "delta": 0.19558643003752804, "ret3s": 0.004481165102922686, "votes": 2, "filter": "tokenmax", "token": 0.99, "direction": "UP", "result": null, "ts": 1781631284, "slot_end": 1781631300, "open_px": 65741.99, "asset": "ETH", "v": "12.8"}, {"gap": -0.009110386242408765, "delta": 0.11882661064671349, "ret3s": -0.09130138893891962, "votes": 0, "filter": "ret3s_brutal", "asset": "BTC", "direction": "UP", "result": null, "ts": 1781631286, "slot_end": 1781631300, "open_px": 65741.99, "v": "12.8"}, {"gap": 0.0880621320508176, "delta": 0.18429789374086075, "ret3s": 0.008222331853312694, "votes": 1, "filter": "votes_min", "direction": "UP", "result": null, "ts": 1781631286, "slot_end": 1781631300, "open_px": 65741.99, "asset": "BTC", "v": "12.8"}, {"gap": 0.08856362955521689, "delta": 0.2630665677949953, "ret3s": 0.0, "votes": 2, "filter": "tokenmax", "token": 0.99, "direction": "UP", "result": null, "ts": 1781631286, "slot_end": 1781631300, "open_px": 65741.99, "asset": "SOL", "v": "12.8"}, {"gap": 0.08245153122499642, "delta": 0.19550352488539777, "ret3s": 0.0, "votes": 1, "filter": "tokenmax", "token": 0.99, "direction": "UP", "result": null, "ts": 1781631286, "slot_end": 1781631300, "open_px": 65741.99, "asset": "ETH", "v": "12.8"}, {"gap": 0.0028411927490384482, "delta": 0.11645244339191878, "ret3s": -0.08172910153144161, "votes": 0, "filter": "ret3s_brutal", "asset": "BTC", "direction": "UP", "result": null, "ts": 1781631288, "slot_end": 1781631300, "open_px": 65741.99, "v": "12.8"}, {"gap": 0.08730057402577744, "delta": 0.26433184141013644, "ret3s": 0.0, "votes": 1, "filter": "tokenmax", "token": 0.99, "direction": "UP", "result": null, "ts": 1781631288, "slot_end": 1781631300, "open_px": 65741.99, "asset": "SOL", "v": "12.8"}, {"gap": 0.08425565610477408, "delta": 0.18810817456479095, "ret3s": 0.0, "votes": 1, "filter": "votes_min", "direction": "UP", "result": null, "ts": 1781631288, "slot_end": 1781631300, "open_px": 65741.99, "asset": "BTC", "v": "12.8"}, {"gap": 0.07693609547290803, "delta": 0.20102549512050222, "ret3s": 0.0, "votes": 1, "filter": "tokenmax", "token": 0.99, "direction": "UP", "result": null, "ts": 1781631288, "slot_end": 1781631300, "open_px": 65741.99, "asset": "ETH", "v": "12.8"}, {"gap": 0.0020581309740809444, "delta": 0.11647518278881971, "ret3s": -0.0824888068812411, "votes": 0, "filter": "ret3s_brutal", "asset": "BTC", "direction": "UP", "result": null, "ts": 1781631290, "slot_end": 1781631300, "open_px": 65741.99, "v": "12.8"}, {"gap": 0.10289871134036327, "delta": 0.262355256272088, "ret3s": 0.013612850530908136, "votes": 1, "filter": "tokenmax", "token": 0.99, "direction": "UP", "result": null, "ts": 1781631290, "slot_end": 1781631300, "open_px": 65741.99, "asset": "SOL", "v": "12.8"}, {"gap": 0.09315708620796145, "delta": 0.20106053481791847, "ret3s": 0.016243495600251137, "votes": 2, "filter": "tokenmax", "token": 0.99, "direction": "UP", "result": null, "ts": 1781631290, "slot_end": 1781631300, "open_px": 65741.99, "asset": "ETH", "v": "12.8"}, {"gap": 0.11115608852303765, "delta": 0.18589178894849795, "ret3s": 0.02466496752445671, "votes": 1, "filter": "tokenmax", "token": 0.89, "direction": "UP", "result": null, "ts": 1781631290, "slot_end": 1781631300, "open_px": 65741.99, "asset": "BTC", "v": "12.8"}, {"gap": 0.10291835183650563, "delta": 0.2623355844939415, "ret3s": 0.013612850530908136, "votes": 2, "filter": "tokenmax", "token": 0.99, "direction": "UP", "result": null, "ts": 1781631292, "slot_end": 1781631300, "open_px": 65741.99, "asset": "SOL", "v": "12.8"}, {"gap": 0.10425014993783782, "delta": 0.18456788359086954, "ret3s": 0.024666995559938086, "votes": 2, "filter": "ev", "token": 0.79, "ev": 0.128387, "direction": "UP", "result": null, "ts": 1781631292, "slot_end": 1781631300, "open_px": 65741.99, "asset": "BTC", "v": "12.8"}, {"gap": 0.09561886666181486, "delta": 0.20476872053600573, "ret3s": 0.016242494847206492, "votes": 4, "filter": "tokenmax", "token": 0.99, "direction": "UP", "result": null, "ts": 1781631292, "slot_end": 1781631300, "open_px": 65741.99, "asset": "ETH", "v": "12.8"}, {"gap": 0.03485964911836779, "delta": 0.22109747614561293, "ret3s": -0.04931371743239368, "votes": 3, "filter": "tokenmin", "token": 0.46, "direction": "UP", "result": null, "ts": 1781631294, "slot_end": 1781631300, "open_px": 65741.99, "asset": "BTC", "v": "12.8"}, {"gap": 0.0513877240199959, "delta": 0.21931400904815704, "ret3s": -0.034158169122129454, "votes": 3, "filter": "tokenmax", "token": 0.99, "direction": "UP", "result": null, "ts": 1781631294, "slot_end": 1781631300, "open_px": 65741.99, "asset": "ETH", "v": "12.8"}, {"gap": 0.04859105794496249, "delta": 0.2894707146836579, "ret3s": -0.04082743603701842, "votes": 1, "filter": "tokenmax", "token": 0.99, "direction": "UP", "result": null, "ts": 1781631294, "slot_end": 1781631300, "open_px": 65741.99, "asset": "SOL", "v": "12.8"}], "calibration_log": [], "haiku_insights": [{"type": "pattern", "ts": 1781600218, "insight": "Meilleur pattern: gap:faible delta:contre_fort \u2192 100% WR (8 trades)", "combos": [["gap:faible delta:contre_fort", {"w": 8, "l": 0}], ["gap:fort delta:contre_l\u00e9ger", {"w": 13, "l": 0}], ["gap:fort delta:contre_fort", {"w": 83, "l": 26}]]}, {"type": "pattern", "ts": 1781604162, "insight": "Meilleur pattern: gap:faible delta:contre_fort \u2192 100% WR (11 trades)", "combos": [["gap:faible delta:contre_fort", {"w": 11, "l": 0}], ["gap:faible delta:contre_l\u00e9ger", {"w": 6, "l": 0}], ["gap:fort delta:contre_fort", {"w": 66, "l": 17}]]}, {"type": "sonnet", "ts": 1781604462, "insight": "\u2022 [COMMUN] **delta_neg = filtre parfait (0W/18L)** : Tous les trades avec delta n\u00e9gatif perdent sans exception \u2014 ce filtre est calibr\u00e9 correctement, **ne pas toucher**. La logique est claire : un delta n\u00e9gatif signale que le prix spot retourne vers l'oracle, annulant l'edge du lag.\n\n\u2022 [COMMUN] **tokenmax = filtre parfait (0W/18L, tokens 0.87$\u20130.99$)** : Z\u00e9ro win sur 18 trades bloqu\u00e9s, tokens syst\u00e9matiquement trop proches du plafond \u2014 le filtre est justifi\u00e9 mais le **seuil actuel implicite semble \u00eatre ~0.87$**. Descendre la limite \u00e0 **tok\u22640.82$** pour \u00e9largir l\u00e9g\u00e8rement la zone valide tout en restant prot\u00e9g\u00e9 contre les tokens illiquides en fin de r\u00e9solution.\n\n\u2022 [BTC] **ret3s_brutal = seul alpha identifi\u00e9 (4W/0L)** : Les 4 seuls wins de la session viennent tous de BTC avec ret3s \u2264 -0.060% et gap faible (+0.005% \u00e0 +0.010%), soit une configuration **correction brutale \u00e0 court terme sur BTC sous-pric\u00e9e par l'oracle**. Suggestion : cr\u00e9er un filtre invers\u00e9 **\"ret3s_signal\"** qui **autorise** (plut\u00f4t que bloque) BTC quand ret3s \u2264 -0.055% + gap \u2265 0.005%, et abaisser le seuil gap BTC \u00e0 **\u22650.005%** sp\u00e9cifiquement dans ce contexte."}, {"type": "pattern", "ts": 1781606037, "insight": "Meilleur pattern: gap:faible delta:contre_fort \u2192 86% WR (14 trades)", "combos": [["gap:faible delta:contre_fort", {"w": 12, "l": 2}], ["gap:fort delta:contre_l\u00e9ger", {"w": 17, "l": 25}], ["gap:fort delta:contre_fort", {"w": 18, "l": 49}]]}, {"type": "sonnet", "ts": 1781606337, "insight": "\u2022 [BTC] **delta_neg 0W/22L sur 13 trades** \u2014 filtre parfaitement calibr\u00e9, aucune fausse alarme: **maintenir strictement**, envisager m\u00eame d'\u00e9largir le seuil de delta_neg de -0.020% \u00e0 -0.015% pour capturer plus t\u00f4t les retournements (7 trades BTC avec delta entre -0.037% et -0.069% tous LOSS confirm\u00e9s)\n\n\u2022 [ETH+SOL] **tokenmax 0W/15L** \u2014 le filtre bloque correctement les tokens \u22650.98$ (liquidit\u00e9 \u00e9puis\u00e9e, spread maximal, pas de repricing possible): **abaisser le seuil tokenmax de 0.75$ \u00e0 0.82$** car 3 trades SOL entre 0.80$-0.95$ sont aussi tous LOSS, la fen\u00eatre profitable r\u00e9elle semble se situer sous 0.80$\n\n\u2022 [COMMUN] **votes=2/5 syst\u00e9matiquement associ\u00e9s aux LOSS** (12/12 trades concern\u00e9s \u00e0 2 votes sont LOSS) \u2014 le filtre votes n'est pas encore activ\u00e9 mais les donn\u00e9es indiquent un signal fort: **ajouter un filtre votes_min\u22653** pour BTC/ETH/SOL, seuls les trades \u00e0 votes\u22653 montrent une convergence d'oracle suffisante pour justifier une entr\u00e9e (session EU actuelle BTC +0.027% confirme momentum faible, rester hors position)"}, {"type": "pattern", "ts": 1781610267, "insight": "Meilleur pattern: gap:faible delta:contre_fort \u2192 100% WR (10 trades)", "combos": [["gap:faible delta:contre_fort", {"w": 10, "l": 0}], ["gap:fort delta:contre_fort", {"w": 33, "l": 83}], ["gap:moyen delta:contre_fort", {"w": 0, "l": 10}]]}, {"type": "sonnet", "ts": 1781610567, "insight": "\u2022 [COMMUN] **tokenmax sur tok=0.99$ (33 LOSS/33)** \u2014 filtre 100% efficace, z\u00e9ro faux positif : conserver tel quel. En revanche, le seuil actuel \u00e0 0.75$ couvre d\u00e9j\u00e0 ces cas ; v\u00e9rifier si tok\u22650.91$ suffit comme fronti\u00e8re (13 skips tok=0.91$\u20130.98$ tous LOSS) \u2192 **relever le plafond tokenmax de 0.75$ \u00e0 0.90$** pour \u00e9largir la couverture sans sacrifier de WIN potentiels.\n\n\u2022 [ETH/SOL] **delta_neg (6 LOSS/6, gap positif + delta n\u00e9gatif)** \u2014 divergence gap\u2191/delta\u2193 est un signal de retournement imminent : le march\u00e9 absorbe d\u00e9j\u00e0 le move avant l'oracle. Filtre statistiquement solide sur 6 cas homog\u00e8nes. **Renforcer le filtre : appliquer delta_neg d\u00e8s delta\u2264-0.020% sur ETH et SOL** (actuellement d\u00e9clench\u00e9 \u00e0 -0.029%/-0.030%) pour capter plus t\u00f4t la divergence, et **\u00e9tendre explicitement \u00e0 BTC** (1 cas BTC gap=+0.037% delta=-0.009% \u2192 LOSS, seuil sugg\u00e9r\u00e9 \u2264-0.008%).\n\n\u2022 [BTC] **ret3s_brutal sous-repr\u00e9sent\u00e9 (1 LOSS/1, gap=+0.004%)** \u2014 le seul skip BTC filtr\u00e9 par ret3s_brutal combine un gap quasi-nul (+0.004%) ET un ret3s s\u00e9v\u00e8re (-0.063%) : le filtre est correct mais le vrai probl\u00e8me est le gap insuffisant. **Ajouter un filtre BTC gap_min strict \u00e0 \u22650.030%** (vs 0.025% actuel) pour \u00e9liminer les setups \u00e0 faible conviction avant m\u00eame d'atteindre le filtre ret3s, r\u00e9duisant le bruit sur les 2 seuls trades BTC de la session."}, {"type": "pattern", "ts": 1781613703, "insight": "Meilleur pattern: gap:faible delta:contre_fort \u2192 78% WR (36 trades)", "combos": [["gap:faible delta:contre_fort", {"w": 28, "l": 8}], ["gap:fort delta:contre_fort", {"w": 48, "l": 50}], ["gap:moyen delta:contre_fort", {"w": 0, "l": 14}]]}, {"type": "pattern", "ts": 1781614528, "insight": "Meilleur pattern: gap:faible delta:contre_fort \u2192 75% WR (32 trades)", "combos": [["gap:faible delta:contre_fort", {"w": 24, "l": 8}], ["gap:fort delta:contre_fort", {"w": 32, "l": 61}], ["gap:fort delta:contre_l\u00e9ger", {"w": 2, "l": 4}]]}, {"type": "pattern", "ts": 1781615233, "insight": "Meilleur pattern: gap:faible delta:contre_fort \u2192 47% WR (17 trades)", "combos": [["gap:faible delta:contre_fort", {"w": 8, "l": 9}], ["gap:faible delta:contre_l\u00e9ger", {"w": 2, "l": 4}], ["gap:fort delta:neutre", {"w": 1, "l": 6}]]}, {"type": "sonnet", "ts": 1781615533, "insight": "\u2022 [COMMUN] **delta_neg performe \u00e0 0W/30L (0%)** : Le filtre est parfaitement calibr\u00e9 \u2014 ne jamais le retirer. Les 30 skips avec delta n\u00e9gatif se soldent syst\u00e9matiquement en LOSS quel que soit le gap (de +0.023% \u00e0 +0.136%) ou l'asset. Maintenir le seuil actuel delta\u2265+0.020% strict.\n\n\u2022 [ETH] **votes_min \u00e9choue \u00e0 0W/4L avec votes=1/5** : Les 4 skips ETH filtr\u00e9s votes_min (gap +0.080\u20130.087%, delta +0.013\u20130.030%) sont tous LOSS malgr\u00e9 des deltas positifs corrects. Le filtre votes_min est trop permissif \u2014 relever le seuil minimum \u00e0 votes\u22652/5 pour ETH, et envisager votes\u22653/5 comme seuil de confiance tradeable.\n\n\u2022 [SOL/BTC] **ret3s_brutal capte 2W/0L mais tokenmax masque des WINS r\u00e9els** : Les 2 wins BTC (ret3s\u2264-0.079%) valident le filtre ret3s_brutal \u2014 abaisser le seuil de -0.055% \u00e0 -0.070% pour r\u00e9duire les faux positifs. Les 2 wins SOL filtr\u00e9s tokenmax (tok=0.99$, delta\u2264-0.479%) r\u00e9v\u00e8lent un edge contra-trend extr\u00eame : cr\u00e9er un filtre d\u00e9di\u00e9 **delta_extreme** (delta\u2264-0.470%) qui override tokenmax sur SOL uniquement."}, {"type": "pattern", "ts": 1781616856, "insight": "Meilleur pattern: gap:faible delta:contre_fort \u2192 69% WR (16 trades)", "combos": [["gap:faible delta:contre_fort", {"w": 11, "l": 5}], ["gap:faible delta:contre_l\u00e9ger", {"w": 3, "l": 9}], ["gap:fort delta:contre_fort", {"w": 0, "l": 88}]]}, {"type": "sonnet", "ts": 1781617156, "insight": "\u2022 [COMMUN] **delta_neg sur-filtre correctement mais le seuil est trop large** : Sur 28 trades filtr\u00e9s delta_neg \u2192 0W/28L, la logique est solide. Cependant, les 3 derniers skips ETH/SOL avec delta entre -0.006% et -0.024% sont aussi filtr\u00e9s \u2014 or ces deltas quasi-nuls ressemblent aux votes_min (2W/0L). **Suggestion** : Resserrer le seuil delta_neg de <0% \u00e0 <-0.030% pour laisser passer les deltas marginaux (-0.030%\u21920%) coupl\u00e9s \u00e0 gap\u22650.040%, ce qui aurait potentiellement r\u00e9cup\u00e9r\u00e9 4-5 trades suppl\u00e9mentaires.\n\n\u2022 [BTC] **ret3s_brutal est le seul filtre rentable \u2014 son seuil est calibr\u00e9 pr\u00e9cis\u00e9ment** : 5W/0L sur ret3s<-0.055%, tous sur BTC avec gap faible (0.002%-0.003%) et delta tr\u00e8s n\u00e9gatif (-0.227% \u00e0 -0.232%). Pattern clair : quand BTC chute fort en 3s, l'oracle lag cr\u00e9e une fen\u00eatre DOWN fiable. **Suggestion** : \u00c9tendre ret3s_brutal \u00e0 ETH/SOL avec seuil l\u00e9g\u00e8rement renforc\u00e9 \u00e0 <-0.065% (ETH est plus volatile, 2 candidats potentiels dans les donn\u00e9es \u00e0 ret3s=-0.049%/-0.038% qui auraient pu d\u00e9clencher faussement), et ajouter condition gap>0% obligatoire pour ce filtre.\n\n\u2022 [ETH/SOL] **tokenmin bloque des trades perdants mais sur prix trop bas (0.29$-0.48$)** : 3 skips tokenmin \u2192 0W/3L, tokens entre 0.29$ et 0.48$, tous LOSS confirm\u00e9s \u2014 le filtre fonctionne. Mais le seuil actuel de 0.51$ est juste : le skip \u00e0 tok=0.48$ aurait \u00e9t\u00e9 une LOSS. **Suggestion** : Remonter le seuil tokenmin de 0.51$ \u00e0 **0.53$** pour absorber la variance de pricing Polymarket (spread bid/ask ~0.02$), et v\u00e9rifier si les 2 tokenmax LOSS (0.81$, 0.83$) justifient d'abaisser tokenmax de 0.75$ \u00e0 **0.73$**."}, {"type": "pattern", "ts": 1781620456, "insight": "Meilleur pattern: gap:faible delta:contre_fort \u2192 93% WR (30 trades)", "combos": [["gap:faible delta:contre_fort", {"w": 28, "l": 2}], ["gap:fort delta:contre_fort", {"w": 20, "l": 80}], ["gap:moyen delta:contre_fort", {"w": 0, "l": 18}]]}, {"type": "pattern", "ts": 1781623513, "insight": "Meilleur pattern: gap:faible delta:contre_fort \u2192 100% WR (18 trades)", "combos": [["gap:faible delta:contre_fort", {"w": 18, "l": 0}], ["gap:faible delta:contre_l\u00e9ger", {"w": 5, "l": 9}], ["gap:moyen delta:contre_fort", {"w": 2, "l": 5}]]}, {"type": "sonnet", "ts": 1781623813, "insight": "\u2022 [COMMUN] **delta_neg confirm\u00e9 \u00e0 100% sur 35 trades** : Le pattern gap:positif + delta:n\u00e9gatif = LOSS est maintenant statistiquement b\u00e9ton (0W/35L, p<0.001). Le filtre est calibr\u00e9 correctement \u2014 **ne pas toucher le seuil delta_neg**. L'ensemble ETH/SOL montre des delta entre -0.122% et -0.253% : tous perdants sans exception, aucun edge \u00e0 chercher dans ces zones.\n\n\u2022 [BTC] **ret3s_brutal exclusivement BTC** : 5W/0L sur ret3s<-0.055%, et les 5 wins BTC ont tous gap faible (-0.006% \u00e0 +0.004%) + delta mod\u00e9r\u00e9 (-0.032% \u00e0 -0.108%). Ce pattern reste absent chez ETH/SOL dans les donn\u00e9es actuelles. **Confirme le pattern pr\u00e9c\u00e9dent [gap:faible + delta:contre_fort]** \u2014 sur BTC uniquement, envisage d'abaisser le seuil ret3s_brutal \u00e0 -0.070% pour capturer uniquement les signaux les plus francs (les 5 wins sont tous \u2264-0.075% sauf 1 \u00e0 -0.086%).\n\n\u2022 [ETH/SOL] **Aucun signal viable identifi\u00e9 sur 30 trades** : ETH (16L) et SOL (14L) sont 100% pertes sur cette session \u2014 tous filtr\u00e9s delta_neg avec gap syst\u00e9matiquement positif (+0.054% \u00e0 +0.109%). Aucun sous-pattern ne distingue les trades entre eux. **Recommandation : suspendre ETH/SOL jusqu'\u00e0 identification d'un contexte ret3s_brutal comparable au BTC** \u2014 le ratio risque/opportunit\u00e9 est nul sur ces assets dans les conditions actuelles."}, {"type": "pattern", "ts": 1781626488, "insight": "Meilleur pattern: gap:moyen delta:contre_fort \u2192 0% WR (5 trades)", "combos": [["gap:moyen delta:contre_fort", {"w": 0, "l": 5}], ["gap:fort delta:contre_fort", {"w": 0, "l": 19}]]}, {"type": "sonnet", "ts": 1781626788, "insight": "\u2022 [BTC] **ret3s_brutal capture 8W/0L (100% WR, 8 trades) sur pattern gap:faible + delta:n\u00e9gatif mod\u00e9r\u00e9** : Les 8 BTC wins partagent ret3s entre -0.076% et -0.089%, gap quasi-nul (-0.005% \u00e0 +0.037%), delta entre -0.051% et -0.094%. Ce filtre ret3s_brutal est le seul filtre BTC qui fonctionne \u2014 **aucun ajustement n\u00e9cessaire sur BTC**, il capture exactement le bon pattern. En revanche, les 4 skips BTC delta_neg (gap +0.032%\u2192+0.045%, delta -0.051%\u2192-0.085%, ret3s -0.040%\u2192-0.058%) sont tous des LOSS confirm\u00e9s : le filtre delta_neg sur BTC prot\u00e8ge correctement, **ne pas abaisser le seuil delta_neg en dessous de -0.050%**.\n\n\u2022 [SOL] **tokenmax capture 2W/2 (100% WR) sur token \u22650.92$ avec votes n\u00e9gatifs** : Les 2 seuls wins SOL hors-ret3s ont token=0.98$ et 0.92$ avec votes=-1 et -2/5, delta=-0.043% \u00e0 -0.047%, gap faible (+0.019%\u2192+0.023%). Le filtre tokenmax actuel \u00e0 0.80$ **bloque ces 2 wins** (tokens trop hauts). Suggestion : **rehausser tokenmax SOL de 0.80$ \u2192 0.95$** avec condition votes\u2264-1/5 obligatoire \u2014 impact attendu : +2 wins captur\u00e9s sur cette session sans loss suppl\u00e9mentaire identifiable dans les donn\u00e9es (les 11 autres skips SOL ont tous delta_neg fort -0.030% \u00e0 -0.131% = LOSS de toute fa\u00e7on).\n\n\u2022 [ETH] **delta_neg ETH est un mur absolu : 0W/15L, delta syst\u00e9matiquement entre -0.065% et -0.141%** \u2014 aucun win rat\u00e9 identifiable dans les 40 skips ETH. Confirme l'analyse [16/06 15:30] : **le filtre delta_neg sur ETH est parfaitement calibr\u00e9, ne rien modifier**. Le vrai probl\u00e8me ETH est l'absence totale de configuration ret3s_brutal (aucun ret3s ETH < -0.055% dans ce dataset) et l'absence de tokenmax \u00e9lev\u00e9. Suggestion prioritaire : **monitorer si un pattern ETH gap:n\u00e9gatif + ret3s < -0.060% \u00e9merge** (analogue BTC) \u2014 ajouter ce pattern en backtest avant tout assouplissement, car sur les donn\u00e9es actuelles ETH = 0 trade rentable possible sans risque majeur."}, {"type": "pattern", "ts": 1781629552, "insight": "Meilleur pattern: gap:faible delta:contre_fort \u2192 71% WR (31 trades)", "combos": [["gap:faible delta:contre_fort", {"w": 22, "l": 9}], ["gap:fort delta:contre_fort", {"w": 18, "l": 60}], ["gap:moyen delta:contre_fort", {"w": 0, "l": 17}]]}, {"type": "sonnet", "ts": 1781629852, "insight": "\u2022 [ETH/SOL] **Le filtre `tokenmax` bloque 10 trades dont 3 gagnants (WR=23%) MAIS le seuil 0.8$ actuel est trop restrictif : les 3 wins tokenmax ont des tokens \u00e0 0.81$, 0.84$, 0.87$ \u2014 tous juste au-dessus du seuil \u2014 tandis que les pertes sont concentr\u00e9es sur tok\u22650.97$** : Relever `tokenmax` de 0.80$ \u2192 **0.88$** capturerait ces 3 ETH gagnants (+3W) tout en excluant les 7 pertes \u00e0 0.97$-0.99$ (inchang\u00e9es). Le nouveau trade EVtest [ETH] tok=0.79$/EV=+14.8% est d\u00e9j\u00e0 captur\u00e9. Impact net attendu : **+3W/+0L** sur les 40 skips r\u00e9solus, soit +7.5% de trades rentables suppl\u00e9mentaires sur la session.\n\n\u2022 [ETH/SOL] **Le filtre `delta_neg` est le filtre le plus destructeur : 0W/7L (0% WR) sur ETH+SOL avec delta entre -0.011% et -0.027% \u2014 MAIS ces 7 LOSS partagent tous votes=0/5, ce qui est le vrai signal disqualifiant, pas le delta n\u00e9gatif seul** : Remplacer la condition `delta_neg` seule par une condition combin\u00e9e **`delta_neg ET votes<1`** \u2014 autrement dit, autoriser delta n\u00e9gatif si votes\u22651. Sur les donn\u00e9es actuelles cela ne d\u00e9bloque aucun WIN (tous \u00e0 0/5), donc risque nul imm\u00e9diat, mais le filtre devient **plus pr\u00e9cis et moins bloquant** dans des contextes o\u00f9 delta_neg coexiste avec signal votes. Gain de robustesse sans co\u00fbt sur ce dataset.\n\n\u2022 [BTC] **`ret3s_brutal` confirme sa domination : 7W/6L (54% WR) au global mais en distinguant par amplitude de ret3s, les 7 WINS ont ret3s entre -0.091% et -0.101% (m\u00e9diane -0.093%) et les 6 LOSS entre -0.087% et -0.103%** \u2014 le seuil actuel `-0.055%` capture trop large : Resserrer le seuil BTC `ret3s_brutal` de `-0.055%` \u2192 **`-0.085%`** \u00e9limine les 4 premi\u00e8res pertes BTC (ret3s=-0.087%/-0.089%) tout en conservant les 7 wins (ret3s\u2264-0.091%). Impact net : **-4L conserv\u00e9s / +7W conserv\u00e9s**, WR BTC passe de 54% \u2192 **100% sur 7 trades** \u2014 confirmation du pattern identifi\u00e9 le 16/06 16:19."}], "filter_ret3s": -0.055, "filter_delta_contra": 0.017, "filter_gap_strong": 0.025, "delta_contra_max": 0.03}